ms_word_parser/__init__.py
ms_word_parser/parse_docx.py
ms_word_parser/tips.py
ms_word_parser-2.0.1.dist-info/licenses/LICENSE
ms_word_parser-2.0.1.dist-info/METADATA
ms_word_parser-2.0.1.dist-info/WHEEL
ms_word_parser-2.0.1.dist-info/entry_points.txt
ms_word_parser-2.0.1.dist-info/top_level.txt
ms_word_parser-2.0.1.dist-info/RECORD
