Metadata-Version: 2.4
Name: ms-word-parser
Version: 2.0.1
Summary: MS Word DOCx Parsing Tool
Author-email: "Jacques Boucher (jjrboucher) and Corey Forman (digitalsleuth)" <jjrboucher@gmail.com>
Maintainer-email: "Jacques Boucher (jjrboucher) and Corey Forman (digitalsleuth)" <jjrboucher@gmail.com>
Project-URL: Homepage, https://github.com/jjrboucher/MS-Word-Parser
Project-URL: References, https://github.com/jjrboucher/MS-Word-Parser/tree/master/Resources
Keywords: digital forensics,dfir,word,docx,parse
Classifier: Development Status :: 5 - Production/Stable
Classifier: Programming Language :: Python :: 3
Classifier: Operating System :: OS Independent
Requires-Python: >=3.9
License-File: LICENSE
Requires-Dist: PyQt6
Requires-Dist: pandas
Requires-Dist: xlsxwriter
Dynamic: license-file
